AUTHORS
LICENSE
MANIFEST.in
README.rst
ping.py
setup.py
python3_ping.egg-info/PKG-INFO
python3_ping.egg-info/SOURCES.txt
python3_ping.egg-info/dependency_links.txt
python3_ping.egg-info/not-zip-safe
python3_ping.egg-info/top_level.txt