Metadata-Version: 1.1
Name: python3-ping
Version: 2014.05.02.16245f0
Summary: A pure python ICMP ping implementation using raw sockets.
Home-page: https://github.com/emamirazavi/python3-ping
Author: Mohammad Emami
Author-email: emamirazavi@gmail.com
License: UNKNOWN
Keywords: ping icmp network latency
Platform: UNKNOWN
Classifier: Development Status :: 5 - Production/Stable
Classifier: Environment :: Web Environment
Classifier: Intended Audience :: Developers
Classifier: Intended Audience :: Education
Classifier: Intended Audience :: End Users/Desktop
Classifier: License :: OSI Approved :: GNU General Public License (GPL)
Classifier: Operating System :: OS Independent
Classifier: Programming Language :: Python
Classifier: Topic :: Internet
Classifier: Topic :: Software Development :: Libraries :: Python Modules
Classifier: Topic :: System :: Networking :: Monitoring
